MANIFEST.in
setup.cfg
setup.py
cheerio/__init__.py
cheerio/__init__.pyc
cheerio/cheerio.py
cheerio/cheerio.pyc
cheerio/goodbye.py
cheerio/goodbye.pyc
cheerio.egg-info/PKG-INFO
cheerio.egg-info/SOURCES.txt
cheerio.egg-info/dependency_links.txt
cheerio.egg-info/entry_points.txt
cheerio.egg-info/not-zip-safe
cheerio.egg-info/top_level.txt