Metadata-Version: 1.0
Name: cheerio
Version: 1.2
Summary: Pseudo-randomly generated goodbyes
Home-page: https://github.com/lucywyman/cheerio
Author: Lucy Wyman
Author-email: wyman.lucy@gmail.com
License: UNKNOWN
Keywords: goodbye,cheerio
Platform: UNKNOWN
